MANIFEST.in
README.rst
setup.py
nose_logpertest/__init__.py
nose_logpertest/logpertest.py
nose_logpertest.egg-info/PKG-INFO
nose_logpertest.egg-info/SOURCES.txt
nose_logpertest.egg-info/dependency_links.txt
nose_logpertest.egg-info/entry_points.txt
nose_logpertest.egg-info/not-zip-safe
nose_logpertest.egg-info/requires.txt
nose_logpertest.egg-info/top_level.txt
tests/__init__.py
tests/config.py
tests/tests_logpertest.py
tests/unittest_runner.py