Metadata-Version: 1.1
Name: nose-logpertest
Version: 0.0.1
Summary: Logging nose plugin to create log per test
Home-page: https://github.com/taykey/nose-logpertest
Author: Roy Klinger
Author-email: roy@taykey.com
License: Apache Software License
Keywords: nosetest logging
Platform: UNKNOWN
Classifier: Programming Language :: Python
Classifier: Development Status :: 4 - Beta
Classifier: Intended Audience :: Developers
Classifier: License :: OSI Approved :: Apache Software License
Classifier: Operating System :: OS Independent
Classifier: Topic :: Software Development :: Testing
